tools_meetup_test/__init__.py
tools_meetup_test/tools_meetup_test.py
simula_tools_meetup_test-0.1.0.dist-info/LICENSE
simula_tools_meetup_test-0.1.0.dist-info/METADATA
simula_tools_meetup_test-0.1.0.dist-info/WHEEL
simula_tools_meetup_test-0.1.0.dist-info/top_level.txt
simula_tools_meetup_test-0.1.0.dist-info/RECORD
