Metadata-Version: 2.1
Name: simula-tools-meetup-test
Version: 0.1.0
Summary: This is a test package for the Simula tools meetup
Home-page: https://github.com/minrk/tools_meetup_test
Author: Min RK
Author-email: benjaminrk@gmail.com
License: BSD license
Keywords: tools_meetup_test
Platform: UNKNOWN
Classifier: Development Status :: 2 - Pre-Alpha
Classifier: Intended Audience :: Developers
Classifier: License :: OSI Approved :: BSD License
Classifier: Natural Language :: English
Classifier: Programming Language :: Python :: 3
Classifier: Programming Language :: Python :: 3.5
Classifier: Programming Language :: Python :: 3.6
Classifier: Programming Language :: Python :: 3.7
Classifier: Programming Language :: Python :: 3.8
Requires-Python: >=3.5
Requires-Dist: numpy
